jpsecurities/__init__.py
jpsecurities/common/__init__.py
jpsecurities/common/request.py
jpsecurities/common/selenium.py
jpsecurities/site/__init__.py
jpsecurities/site/gmo.py
jpsecurities/site/kabutan.py
jpsecurities/site/rakuten.py
jpsecurities/site/sbi.py
jpsecurities/site/taisyaku.py
jpsecurities/site/yahoo.py
jpsecurities/tool/__init__.py
jpsecurities/tool/holiday.py
jpsecurities/tool/kasikabu.py
jpsecurities/util/__init__.py
jpsecurities/util/holiday.py
jpsecurities/util/kasikabu.py
jpsecurities/util/request.py
jpsecurities/util/selenium.py
tests/__init__.py
tests/site/__init__.py
tests/site/gmo.py
tests/site/kabutan.py
tests/site/rakuten.py
tests/site/sbi.py
tests/site/taisyaku.py
tests/site/yahoo.py
tests/tool/__init__.py
tests/tool/holiday.py
tests/tool/kasikabu.py
jpsecurities-0.2.5.0.dist-info/METADATA
jpsecurities-0.2.5.0.dist-info/WHEEL
jpsecurities-0.2.5.0.dist-info/top_level.txt
jpsecurities-0.2.5.0.dist-info/RECORD
