Metadata-Version: 2.1
Name: jpsecurities
Version: 0.2.5.0
Summary: API for jp securities
Home-page: https://rescala.jp
Author: rv
Author-email: yo-maruya@rescala.jp
License: MIT
Project-URL: Bug Reports, https://github.com/rv-rescala/jpsecurities/issues
Project-URL: Source, https://github.com/rv-rescala/jpsecurities
Keywords: python crawler scraping
Platform: UNKNOWN
Requires-Python: >=3.7
Requires-Dist: requests
Requires-Dist: bs4
Requires-Dist: selenium
Requires-Dist: lxml
Requires-Dist: pandas
Requires-Dist: openpyxl
Requires-Dist: numpy
